django_ldap/__init__.py
django_ldap/backend.py
django_ldap/ldap.py
django_ldap/settings.py
django_ldap/utils.py
django_ldap/version.py
django_ldap/management/__init__.py
django_ldap/management/commands/__init__.py
django_ldap/management/commands/_private.py
django_ldap/management/commands/ldap_attempt_bind.py
django_ldap-0.0.8.dist-info/LICENSE
django_ldap-0.0.8.dist-info/METADATA
django_ldap-0.0.8.dist-info/WHEEL
django_ldap-0.0.8.dist-info/top_level.txt
django_ldap-0.0.8.dist-info/RECORD
