Metadata-Version: 2.1
Name: django-ldap
Version: 0.0.8
Summary: Django LDAP3.
Home-page: https://github.com/strife-dev/django-ldap
Author: Strife-Dev
License: BSD-3-Clause
Project-URL: Documentation, https://github.com/strife-dev/django-ldap/blob/master/documentation/readme.md
Project-URL: Source, https://github.com/strife-dev/django-ldap
Project-URL: Tracker, https://github.com/strife-dev/django-ldap/issues
Platform: UNKNOWN
Classifier: Development Status :: 2 - Pre-Alpha
Classifier: Environment :: Web Environment
Classifier: Framework :: Django
Classifier: Framework :: Django :: 2.2
Classifier: Framework :: Django :: 3.1
Classifier: Framework :: Django :: 3.2
Classifier: Intended Audience :: Developers
Classifier: Intended Audience :: System Administrators
Classifier: License :: OSI Approved :: BSD License
Classifier: Programming Language :: Python
Classifier: Programming Language :: Python :: 3
Classifier: Programming Language :: Python :: 3 :: Only
Classifier: Programming Language :: Python :: 3.7
Classifier: Programming Language :: Python :: 3.8
Classifier: Programming Language :: Python :: 3.9
Classifier: Topic :: Internet :: WWW/HTTP
Classifier: Topic :: Software Development :: Libraries :: Python Modules
Classifier: Topic :: System :: Systems Administration :: Authentication/Directory :: LDAP
Requires-Python: >=3.7
License-File: LICENSE
Requires-Dist: django (>=2.2)
Requires-Dist: ldap3 (>=2.7)
Requires-Dist: pytest (>=3.9)
